tdsreduction/__init__.py
tdsreduction/bias.py
tdsreduction/corrections.py
tdsreduction/cosmics.py
tdsreduction/dark.py
tdsreduction/dispersion.py
tdsreduction/distorsion.py
tdsreduction/flat.py
tdsreduction/genfuncs.py
tdsreduction/geometry.py
tdsreduction/pipeline.py
tdsreduction/sky.py
tdsreduction-0.1.0.dev2.data/scripts/tdspipeline
tdsreduction-0.1.0.dev2.dist-info/LICENSE
tdsreduction-0.1.0.dev2.dist-info/METADATA
tdsreduction-0.1.0.dev2.dist-info/WHEEL
tdsreduction-0.1.0.dev2.dist-info/top_level.txt
tdsreduction-0.1.0.dev2.dist-info/RECORD
